{
    "data": [
        {
            "id": 0,
            "message": "CRUD 공부하기",
            "date": "2024-01-23",
            "state": false
        },
        {
            "id": 1,
            "message": "React 복습하기",
            "date": "2024-01-23",
            "state": true
        },
        {
            "id": 1706000864969,
            "message": "이거 성공하기",
            "date": "2024-1-23",
            "state": false
        },
        {
            "id": 1706057051726,
            "message": "asdfa",
            "date": "2024-1-24",
            "state": false
        },
        {
            "id": 1706063225808,
            "message": "",
            "date": "2024-1-24",
            "state": false
        }
    ]
}